frt/FF3.py
frt/FetchData.py
frt/__init__.py
frt-0.0.1.dist-info/LICENSE
frt-0.0.1.dist-info/METADATA
frt-0.0.1.dist-info/WHEEL
frt-0.0.1.dist-info/top_level.txt
frt-0.0.1.dist-info/RECORD
