Metadata-Version: 2.1
Name: frt
Version: 0.0.1
Summary: A package for financial research using WRDS data
Home-page: https://github.com/vanBrakel/FRT
Author: Jean-Paul van Brakel
Author-email: jeanpaulvbrakel@gmail.com
License: UNKNOWN
Platform: UNKNOWN
Classifier: Programming Language :: Python :: 3
Classifier: License :: OSI Approved :: MIT License
Classifier: Operating System :: OS Independent
Requires-Python: >=3.6
